{
    "text": "Value Serp",
    "href": "https://www.valueserp.com/docs",
    "children": [
        {
            "text": "Account API",
            "href": "https://www.serpwow.com/docs/account-api"
        },
        {
            "text": "Product Updates",
            "href": "https://www.serpwow.com/docs/product-updates"
        },
        {
            "text": "Response Codes",
            "href": "https://www.serpwow.com/docs/response-codes"
        },
        {
            "text": "Account API",
            "href": "https://www.scaleserp.com/docs/account-api"
        },
        {
            "text": "Product Updates",
            "href": "https://www.scaleserp.com/docs/product-updates"
        },
        {
            "text": "Response Codes",
            "href": "https://www.scaleserp.com/docs/response-codes"
        },
        {
            "text": "Account API",
            "href": "https://www.valueserp.com/docs/account-api"
        },
        {
            "text": "Product Updates",
            "href": "https://www.valueserp.com/docs/product-updates"
        },
        {
            "text": "Response Codes",
            "href": "https://www.valueserp.com/docs/response-codes"
        }
    ]
}